odoo8_addon_web_menu_collapsible-8.0.1.0.0-py2.7-nspkg.pth
odoo8_addon_web_menu_collapsible-8.0.1.0.0.dist-info/top_level.txt
odoo8_addon_web_menu_collapsible-8.0.1.0.0.dist-info/WHEEL
odoo8_addon_web_menu_collapsible-8.0.1.0.0.dist-info/RECORD
odoo8_addon_web_menu_collapsible-8.0.1.0.0.dist-info/metadata.json
odoo8_addon_web_menu_collapsible-8.0.1.0.0.dist-info/DESCRIPTION.rst
odoo8_addon_web_menu_collapsible-8.0.1.0.0.dist-info/METADATA
odoo8_addon_web_menu_collapsible-8.0.1.0.0.dist-info/namespace_packages.txt
odoo_addons/web_menu_collapsible/__openerp__.py
odoo_addons/web_menu_collapsible/__init__.py
odoo_addons/web_menu_collapsible/README.rst
odoo_addons/web_menu_collapsible/templates/menu_collapsible.xml
odoo_addons/web_menu_collapsible/static/description/menu_collapsible_2.png
odoo_addons/web_menu_collapsible/static/description/menu_collapsible_1.png
odoo_addons/web_menu_collapsible/static/description/icon.png
odoo_addons/web_menu_collapsible/static/src/js/menu_collapsible.js
odoo_addons/web_menu_collapsible/static/src/css/menu_collapsible.css
